cinnamon_udev_locker/__init__.py
cinnamon_udev_locker/main.py
cinnamon_udev_locker-0.1.0.dist-info/DESCRIPTION.rst
cinnamon_udev_locker-0.1.0.dist-info/METADATA
cinnamon_udev_locker-0.1.0.dist-info/RECORD
cinnamon_udev_locker-0.1.0.dist-info/WHEEL
cinnamon_udev_locker-0.1.0.dist-info/entry_points.txt
cinnamon_udev_locker-0.1.0.dist-info/metadata.json
cinnamon_udev_locker-0.1.0.dist-info/top_level.txt
