Metadata-Version: 2.0
Name: cinnamon-udev-locker
Version: 0.1.0
Summary: Lock Cinnamon desktop session on device removal (i.e YubiKey)
Home-page: https://github.com/fladi/cinnamon-udev-locker
Author: Michael Fladischer
Author-email: michael@fladi.at
License: UNKNOWN
Platform: UNKNOWN
Classifier: Development Status :: 2 - Pre-Alpha
Classifier: Environment :: X11 Applications :: GTK
Classifier: Intended Audience :: End Users/Desktop
Classifier: License :: OSI Approved :: MIT License
Classifier: Operating System :: POSIX :: Linux
Classifier: Topic :: Desktop Environment :: Screen Savers
Classifier: Topic :: Security
Classifier: Topic :: Utilities
Classifier: Programming Language :: Python :: 3 :: Only
Classifier: Programming Language :: Python :: 3.5
Classifier: Programming Language :: Python :: 3.6
Requires-Dist: click
Requires-Dist: click-log
Requires-Dist: pygobject
Requires-Dist: pyxdg
